youtube2text/__init__.py
youtube2text/youtube2text.py
youtube2text-0.0.9.dist-info/LICENSE
youtube2text-0.0.9.dist-info/METADATA
youtube2text-0.0.9.dist-info/WHEEL
youtube2text-0.0.9.dist-info/top_level.txt
youtube2text-0.0.9.dist-info/RECORD
