Metadata-Version: 2.1
Name: youtube2text
Version: 0.0.9
Summary: Convert youtube urls to text with speech recognition
Home-page: https://github.com/codenamewei/youtube2text
Author: codenamewei
Author-email: codenamewei@gmail.com
License: MIT
Platform: UNKNOWN
Classifier: Programming Language :: Python :: 3
Classifier: License :: OSI Approved :: MIT License
Classifier: Operating System :: OS Independent
Requires-Python: >=3.6
License-File: LICENSE
Requires-Dist: pytube (>=12.0.0)
Requires-Dist: numpy (<=1.21.5)
Requires-Dist: pytube (>=11.0.2)
Requires-Dist: pydub (>=0.25.1)
Requires-Dist: SpeechRecognition (>=3.8.1)
Requires-Dist: pandas (>=1.1.5)
Requires-Dist: ffmpeg-python (>=0.2.0)
Requires-Dist: librosa (>=0.8.1)
Requires-Dist: soundfile (<=0.10.3post1)
